Metadata-Version: 2.1
Name: ansible-compose
Version: 1.0.8
Summary: The obscene docker-compose deploy with ansible cli
Home-page: https://yourlabs.io/oss/ansible-compose
Author: James Pic
Author-email: jamespic@gmail.com
License: UNKNOWN
Platform: UNKNOWN
Classifier: Development Status :: 3 - Alpha
Classifier: Environment :: Console
Classifier: Intended Audience :: System Administrators
Classifier: License :: OSI Approved :: MIT License
Classifier: Programming Language :: Python :: 3 :: Only
Classifier: Topic :: Software Development
Classifier: Topic :: System
